ambrogio/__init__.py
ambrogio/__main__.py
ambrogio/cli/__init__.py
ambrogio/cli/dashboard.py
ambrogio/cli/logger.py
ambrogio/cli/prompt.py
ambrogio/cli/start.py
ambrogio/environment/__init__.py
ambrogio/procedures/__init__.py
ambrogio/procedures/basic.py
ambrogio/procedures/loader.py
ambrogio/procedures/param.py
ambrogio/procedures/step.py
ambrogio/procedures/templates/basic.py.tmpl
ambrogio/procedures/templates/step.py.tmpl
ambrogio/utils/__init__.py
ambrogio/utils/memory.py
ambrogio/utils/project.py
ambrogio/utils/threading.py
ambrogio/utils/time.py
ambrogio-0.6.1.dist-info/LICENSE
ambrogio-0.6.1.dist-info/METADATA
ambrogio-0.6.1.dist-info/WHEEL
ambrogio-0.6.1.dist-info/entry_points.txt
ambrogio-0.6.1.dist-info/top_level.txt
ambrogio-0.6.1.dist-info/RECORD
