Metadata-Version: 2.1
Name: ambrogio
Version: 0.6.1
Summary: A simple framework to handle complex scripts.
Home-page: https://github.com/officinaMusci/ambrogio
Author: Danilo Musci
Author-email: officina@musci.ch
License: BSD 3-Clause
Project-URL: Source, https://github.com/officinaMusci/ambrogio
Project-URL: Tracker, https://github.com/officinaMusci/ambrogio/issues
Classifier: Development Status :: 1 - Planning
Classifier: Environment :: Console
Classifier: Intended Audience :: Developers
Classifier: Programming Language :: Python
Classifier: Programming Language :: Python :: 3.7
Classifier: Programming Language :: Python :: 3.8
Classifier: Programming Language :: Python :: 3.9
Classifier: Programming Language :: Python :: 3.10
Classifier: Programming Language :: Python :: 3.11
Classifier: License :: OSI Approved :: BSD License
Classifier: Operating System :: OS Independent
Classifier: Topic :: Software Development :: Libraries :: Application Frameworks
Classifier: Topic :: Software Development :: Libraries :: Python Modules
Requires-Python: >=3.7
License-File: LICENSE
Requires-Dist: setuptools
Requires-Dist: psutil
Requires-Dist: inquirer
Requires-Dist: rich
Requires-Dist: plotly
